{
    "dataset_revision": "75b399394a9803252cfec289d103de462763db7c",
    "task_name": "BelebeleRetrieval",
    "mteb_version": "1.39.7",
    "scores": {
        "test": [
            {
                "ndcg_at_1": 0.51778,
                "ndcg_at_3": 0.60012,
                "ndcg_at_5": 0.62168,
                "ndcg_at_10": 0.64573,
                "ndcg_at_20": 0.66042,
                "ndcg_at_100": 0.68002,
                "ndcg_at_1000": 0.68694,
                "map_at_1": 0.51778,
                "map_at_3": 0.57981,
                "map_at_5": 0.59181,
                "map_at_10": 0.60194,
                "map_at_20": 0.60588,
                "map_at_100": 0.60867,
                "map_at_1000": 0.60896,
                "recall_at_1": 0.51778,
                "recall_at_3": 0.65889,
                "recall_at_5": 0.71111,
                "recall_at_10": 0.78444,
                "recall_at_20": 0.84333,
                "recall_at_100": 0.94778,
                "recall_at_1000": 1.0,
                "precision_at_1": 0.51778,
                "precision_at_3": 0.21963,
                "precision_at_5": 0.14222,
                "precision_at_10": 0.07844,
                "precision_at_20": 0.04217,
                "precision_at_100": 0.00948,
                "precision_at_1000": 0.001,
                "mrr_at_1": 0.517778,
                "mrr_at_3": 0.579815,
                "mrr_at_5": 0.591815,
                "mrr_at_10": 0.60194,
                "mrr_at_20": 0.605876,
                "mrr_at_100": 0.608665,
                "mrr_at_1000": 0.60896,
                "nauc_ndcg_at_1_max": 0.637598,
                "nauc_ndcg_at_1_std": 0.002624,
                "nauc_ndcg_at_1_diff1": 0.728542,
                "nauc_ndcg_at_3_max": 0.655696,
                "nauc_ndcg_at_3_std": 0.024922,
                "nauc_ndcg_at_3_diff1": 0.683295,
                "nauc_ndcg_at_5_max": 0.646523,
                "nauc_ndcg_at_5_std": 0.009714,
                "nauc_ndcg_at_5_diff1": 0.675009,
                "nauc_ndcg_at_10_max": 0.646066,
                "nauc_ndcg_at_10_std": 0.016386,
                "nauc_ndcg_at_10_diff1": 0.673922,
                "nauc_ndcg_at_20_max": 0.640707,
                "nauc_ndcg_at_20_std": 0.00609,
                "nauc_ndcg_at_20_diff1": 0.673583,
                "nauc_ndcg_at_100_max": 0.644535,
                "nauc_ndcg_at_100_std": 0.01736,
                "nauc_ndcg_at_100_diff1": 0.680564,
                "nauc_ndcg_at_1000_max": 0.643533,
                "nauc_ndcg_at_1000_std": 0.011905,
                "nauc_ndcg_at_1000_diff1": 0.683347,
                "nauc_map_at_1_max": 0.637598,
                "nauc_map_at_1_std": 0.002624,
                "nauc_map_at_1_diff1": 0.728542,
                "nauc_map_at_3_max": 0.650352,
                "nauc_map_at_3_std": 0.018372,
                "nauc_map_at_3_diff1": 0.694797,
                "nauc_map_at_5_max": 0.645237,
                "nauc_map_at_5_std": 0.01041,
                "nauc_map_at_5_diff1": 0.690496,
                "nauc_map_at_10_max": 0.644766,
                "nauc_map_at_10_std": 0.012388,
                "nauc_map_at_10_diff1": 0.690189,
                "nauc_map_at_20_max": 0.643368,
                "nauc_map_at_20_std": 0.00991,
                "nauc_map_at_20_diff1": 0.690312,
                "nauc_map_at_100_max": 0.643676,
                "nauc_map_at_100_std": 0.01103,
                "nauc_map_at_100_diff1": 0.691094,
                "nauc_map_at_1000_max": 0.643643,
                "nauc_map_at_1000_std": 0.01083,
                "nauc_map_at_1000_diff1": 0.691186,
                "nauc_recall_at_1_max": 0.637598,
                "nauc_recall_at_1_std": 0.002624,
                "nauc_recall_at_1_diff1": 0.728542,
                "nauc_recall_at_3_max": 0.673358,
                "nauc_recall_at_3_std": 0.046559,
                "nauc_recall_at_3_diff1": 0.646041,
                "nauc_recall_at_5_max": 0.650037,
                "nauc_recall_at_5_std": 0.004567,
                "nauc_recall_at_5_diff1": 0.6187,
                "nauc_recall_at_10_max": 0.651145,
                "nauc_recall_at_10_std": 0.036799,
                "nauc_recall_at_10_diff1": 0.600972,
                "nauc_recall_at_20_max": 0.616128,
                "nauc_recall_at_20_std": -0.03027,
                "nauc_recall_at_20_diff1": 0.574108,
                "nauc_recall_at_100_max": 0.680513,
                "nauc_recall_at_100_std": 0.205713,
                "nauc_recall_at_100_diff1": 0.580964,
                "nauc_recall_at_1000_max": NaN,
                "nauc_recall_at_1000_std": NaN,
                "nauc_recall_at_1000_diff1": NaN,
                "nauc_precision_at_1_max": 0.637598,
                "nauc_precision_at_1_std": 0.002624,
                "nauc_precision_at_1_diff1": 0.728542,
                "nauc_precision_at_3_max": 0.673358,
                "nauc_precision_at_3_std": 0.046559,
                "nauc_precision_at_3_diff1": 0.646041,
                "nauc_precision_at_5_max": 0.650037,
                "nauc_precision_at_5_std": 0.004567,
                "nauc_precision_at_5_diff1": 0.6187,
                "nauc_precision_at_10_max": 0.651145,
                "nauc_precision_at_10_std": 0.036799,
                "nauc_precision_at_10_diff1": 0.600972,
                "nauc_precision_at_20_max": 0.616128,
                "nauc_precision_at_20_std": -0.03027,
                "nauc_precision_at_20_diff1": 0.574108,
                "nauc_precision_at_100_max": 0.680513,
                "nauc_precision_at_100_std": 0.205713,
                "nauc_precision_at_100_diff1": 0.580964,
                "nauc_precision_at_1000_max": NaN,
                "nauc_precision_at_1000_std": NaN,
                "nauc_precision_at_1000_diff1": NaN,
                "nauc_mrr_at_1_max": 0.637598,
                "nauc_mrr_at_1_std": 0.002624,
                "nauc_mrr_at_1_diff1": 0.728542,
                "nauc_mrr_at_3_max": 0.650352,
                "nauc_mrr_at_3_std": 0.018372,
                "nauc_mrr_at_3_diff1": 0.694797,
                "nauc_mrr_at_5_max": 0.645237,
                "nauc_mrr_at_5_std": 0.01041,
                "nauc_mrr_at_5_diff1": 0.690496,
                "nauc_mrr_at_10_max": 0.644766,
                "nauc_mrr_at_10_std": 0.012388,
                "nauc_mrr_at_10_diff1": 0.690189,
                "nauc_mrr_at_20_max": 0.643368,
                "nauc_mrr_at_20_std": 0.00991,
                "nauc_mrr_at_20_diff1": 0.690312,
                "nauc_mrr_at_100_max": 0.643676,
                "nauc_mrr_at_100_std": 0.01103,
                "nauc_mrr_at_100_diff1": 0.691094,
                "nauc_mrr_at_1000_max": 0.643643,
                "nauc_mrr_at_1000_std": 0.01083,
                "nauc_mrr_at_1000_diff1": 0.691186,
                "main_score": 0.64573,
                "hf_subset": "slk_Latn-slk_Latn",
                "languages": [
                    "slk-Latn",
                    "slk-Latn"
                ]
            },
            {
                "ndcg_at_1": 0.52,
                "ndcg_at_3": 0.60278,
                "ndcg_at_5": 0.62487,
                "ndcg_at_10": 0.65065,
                "ndcg_at_20": 0.66284,
                "ndcg_at_100": 0.68239,
                "ndcg_at_1000": 0.68929,
                "map_at_1": 0.52,
                "map_at_3": 0.58259,
                "map_at_5": 0.59493,
                "map_at_10": 0.60551,
                "map_at_20": 0.60891,
                "map_at_100": 0.6116,
                "map_at_1000": 0.61189,
                "recall_at_1": 0.52,
                "recall_at_3": 0.66111,
                "recall_at_5": 0.71444,
                "recall_at_10": 0.79444,
                "recall_at_20": 0.84222,
                "recall_at_100": 0.94778,
                "recall_at_1000": 1.0,
                "precision_at_1": 0.52,
                "precision_at_3": 0.22037,
                "precision_at_5": 0.14289,
                "precision_at_10": 0.07944,
                "precision_at_20": 0.04211,
                "precision_at_100": 0.00948,
                "precision_at_1000": 0.001,
                "mrr_at_1": 0.52,
                "mrr_at_3": 0.582593,
                "mrr_at_5": 0.594926,
                "mrr_at_10": 0.60551,
                "mrr_at_20": 0.608909,
                "mrr_at_100": 0.611604,
                "mrr_at_1000": 0.611893,
                "nauc_ndcg_at_1_max": 0.496871,
                "nauc_ndcg_at_1_std": -0.109585,
                "nauc_ndcg_at_1_diff1": 0.675368,
                "nauc_ndcg_at_3_max": 0.54149,
                "nauc_ndcg_at_3_std": -0.106089,
                "nauc_ndcg_at_3_diff1": 0.640356,
                "nauc_ndcg_at_5_max": 0.538506,
                "nauc_ndcg_at_5_std": -0.101134,
                "nauc_ndcg_at_5_diff1": 0.631417,
                "nauc_ndcg_at_10_max": 0.537866,
                "nauc_ndcg_at_10_std": -0.096568,
                "nauc_ndcg_at_10_diff1": 0.636035,
                "nauc_ndcg_at_20_max": 0.537028,
                "nauc_ndcg_at_20_std": -0.090867,
                "nauc_ndcg_at_20_diff1": 0.637195,
                "nauc_ndcg_at_100_max": 0.533054,
                "nauc_ndcg_at_100_std": -0.101495,
                "nauc_ndcg_at_100_diff1": 0.638706,
                "nauc_ndcg_at_1000_max": 0.532653,
                "nauc_ndcg_at_1000_std": -0.101514,
                "nauc_ndcg_at_1000_diff1": 0.642248,
                "nauc_map_at_1_max": 0.496871,
                "nauc_map_at_1_std": -0.109585,
                "nauc_map_at_1_diff1": 0.675368,
                "nauc_map_at_3_max": 0.532262,
                "nauc_map_at_3_std": -0.107691,
                "nauc_map_at_3_diff1": 0.64976,
                "nauc_map_at_5_max": 0.530753,
                "nauc_map_at_5_std": -0.104707,
                "nauc_map_at_5_diff1": 0.64522,
                "nauc_map_at_10_max": 0.530204,
                "nauc_map_at_10_std": -0.103378,
                "nauc_map_at_10_diff1": 0.647437,
                "nauc_map_at_20_max": 0.529967,
                "nauc_map_at_20_std": -0.102057,
                "nauc_map_at_20_diff1": 0.647974,
                "nauc_map_at_100_max": 0.529243,
                "nauc_map_at_100_std": -0.103762,
                "nauc_map_at_100_diff1": 0.64814,
                "nauc_map_at_1000_max": 0.529253,
                "nauc_map_at_1000_std": -0.103773,
                "nauc_map_at_1000_diff1": 0.648254,
                "nauc_recall_at_1_max": 0.496871,
                "nauc_recall_at_1_std": -0.109585,
                "nauc_recall_at_1_diff1": 0.675368,
                "nauc_recall_at_3_max": 0.570364,
                "nauc_recall_at_3_std": -0.100557,
                "nauc_recall_at_3_diff1": 0.609654,
                "nauc_recall_at_5_max": 0.564046,
                "nauc_recall_at_5_std": -0.087712,
                "nauc_recall_at_5_diff1": 0.580272,
                "nauc_recall_at_10_max": 0.569758,
                "nauc_recall_at_10_std": -0.060805,
                "nauc_recall_at_10_diff1": 0.584197,
                "nauc_recall_at_20_max": 0.572057,
                "nauc_recall_at_20_std": -0.011347,
                "nauc_recall_at_20_diff1": 0.576187,
                "nauc_recall_at_100_max": 0.553271,
                "nauc_recall_at_100_std": -0.103681,
                "nauc_recall_at_100_diff1": 0.510251,
                "nauc_recall_at_1000_max": NaN,
                "nauc_recall_at_1000_std": NaN,
                "nauc_recall_at_1000_diff1": NaN,
                "nauc_precision_at_1_max": 0.496871,
                "nauc_precision_at_1_std": -0.109585,
                "nauc_precision_at_1_diff1": 0.675368,
                "nauc_precision_at_3_max": 0.570364,
                "nauc_precision_at_3_std": -0.100557,
                "nauc_precision_at_3_diff1": 0.609654,
                "nauc_precision_at_5_max": 0.564046,
                "nauc_precision_at_5_std": -0.087712,
                "nauc_precision_at_5_diff1": 0.580272,
                "nauc_precision_at_10_max": 0.569758,
                "nauc_precision_at_10_std": -0.060805,
                "nauc_precision_at_10_diff1": 0.584197,
                "nauc_precision_at_20_max": 0.572057,
                "nauc_precision_at_20_std": -0.011347,
                "nauc_precision_at_20_diff1": 0.576187,
                "nauc_precision_at_100_max": 0.553271,
                "nauc_precision_at_100_std": -0.103681,
                "nauc_precision_at_100_diff1": 0.510251,
                "nauc_precision_at_1000_max": NaN,
                "nauc_precision_at_1000_std": NaN,
                "nauc_precision_at_1000_diff1": NaN,
                "nauc_mrr_at_1_max": 0.496871,
                "nauc_mrr_at_1_std": -0.109585,
                "nauc_mrr_at_1_diff1": 0.675368,
                "nauc_mrr_at_3_max": 0.532262,
                "nauc_mrr_at_3_std": -0.107691,
                "nauc_mrr_at_3_diff1": 0.64976,
                "nauc_mrr_at_5_max": 0.530753,
                "nauc_mrr_at_5_std": -0.104707,
                "nauc_mrr_at_5_diff1": 0.64522,
                "nauc_mrr_at_10_max": 0.530204,
                "nauc_mrr_at_10_std": -0.103378,
                "nauc_mrr_at_10_diff1": 0.647437,
                "nauc_mrr_at_20_max": 0.529967,
                "nauc_mrr_at_20_std": -0.102057,
                "nauc_mrr_at_20_diff1": 0.647974,
                "nauc_mrr_at_100_max": 0.529243,
                "nauc_mrr_at_100_std": -0.103762,
                "nauc_mrr_at_100_diff1": 0.64814,
                "nauc_mrr_at_1000_max": 0.529253,
                "nauc_mrr_at_1000_std": -0.103773,
                "nauc_mrr_at_1000_diff1": 0.648254,
                "main_score": 0.65065,
                "hf_subset": "slk_Latn-eng_Latn",
                "languages": [
                    "slk-Latn",
                    "eng-Latn"
                ]
            },
            {
                "ndcg_at_1": 0.41556,
                "ndcg_at_3": 0.50645,
                "ndcg_at_5": 0.52558,
                "ndcg_at_10": 0.55192,
                "ndcg_at_20": 0.57149,
                "ndcg_at_100": 0.59691,
                "ndcg_at_1000": 0.60845,
                "map_at_1": 0.41556,
                "map_at_3": 0.48444,
                "map_at_5": 0.495,
                "map_at_10": 0.50594,
                "map_at_20": 0.51141,
                "map_at_100": 0.5148,
                "map_at_1000": 0.5153,
                "recall_at_1": 0.41556,
                "recall_at_3": 0.57,
                "recall_at_5": 0.61667,
                "recall_at_10": 0.69778,
                "recall_at_20": 0.77444,
                "recall_at_100": 0.91333,
                "recall_at_1000": 1.0,
                "precision_at_1": 0.41556,
                "precision_at_3": 0.19,
                "precision_at_5": 0.12333,
                "precision_at_10": 0.06978,
                "precision_at_20": 0.03872,
                "precision_at_100": 0.00913,
                "precision_at_1000": 0.001,
                "mrr_at_1": 0.415556,
                "mrr_at_3": 0.484444,
                "mrr_at_5": 0.495,
                "mrr_at_10": 0.505942,
                "mrr_at_20": 0.511414,
                "mrr_at_100": 0.514798,
                "mrr_at_1000": 0.515305,
                "nauc_ndcg_at_1_max": 0.536972,
                "nauc_ndcg_at_1_std": 0.020363,
                "nauc_ndcg_at_1_diff1": 0.656342,
                "nauc_ndcg_at_3_max": 0.531375,
                "nauc_ndcg_at_3_std": 0.028479,
                "nauc_ndcg_at_3_diff1": 0.606281,
                "nauc_ndcg_at_5_max": 0.530955,
                "nauc_ndcg_at_5_std": 0.018377,
                "nauc_ndcg_at_5_diff1": 0.603099,
                "nauc_ndcg_at_10_max": 0.539387,
                "nauc_ndcg_at_10_std": 0.033734,
                "nauc_ndcg_at_10_diff1": 0.605389,
                "nauc_ndcg_at_20_max": 0.536647,
                "nauc_ndcg_at_20_std": 0.034657,
                "nauc_ndcg_at_20_diff1": 0.59901,
                "nauc_ndcg_at_100_max": 0.533912,
                "nauc_ndcg_at_100_std": 0.032868,
                "nauc_ndcg_at_100_diff1": 0.603268,
                "nauc_ndcg_at_1000_max": 0.535799,
                "nauc_ndcg_at_1000_std": 0.029987,
                "nauc_ndcg_at_1000_diff1": 0.609639,
                "nauc_map_at_1_max": 0.536972,
                "nauc_map_at_1_std": 0.020363,
                "nauc_map_at_1_diff1": 0.656342,
                "nauc_map_at_3_max": 0.532344,
                "nauc_map_at_3_std": 0.025791,
                "nauc_map_at_3_diff1": 0.618647,
                "nauc_map_at_5_max": 0.532084,
                "nauc_map_at_5_std": 0.020714,
                "nauc_map_at_5_diff1": 0.616964,
                "nauc_map_at_10_max": 0.536093,
                "nauc_map_at_10_std": 0.026747,
                "nauc_map_at_10_diff1": 0.618638,
                "nauc_map_at_20_max": 0.535546,
                "nauc_map_at_20_std": 0.027059,
                "nauc_map_at_20_diff1": 0.617044,
                "nauc_map_at_100_max": 0.535324,
                "nauc_map_at_100_std": 0.026918,
                "nauc_map_at_100_diff1": 0.617503,
                "nauc_map_at_1000_max": 0.535408,
                "nauc_map_at_1000_std": 0.0268,
                "nauc_map_at_1000_diff1": 0.617832,
                "nauc_recall_at_1_max": 0.536972,
                "nauc_recall_at_1_std": 0.020363,
                "nauc_recall_at_1_diff1": 0.656342,
                "nauc_recall_at_3_max": 0.528593,
                "nauc_recall_at_3_std": 0.037015,
                "nauc_recall_at_3_diff1": 0.568422,
                "nauc_recall_at_5_max": 0.527509,
                "nauc_recall_at_5_std": 0.008924,
                "nauc_recall_at_5_diff1": 0.558105,
                "nauc_recall_at_10_max": 0.554046,
                "nauc_recall_at_10_std": 0.065361,
                "nauc_recall_at_10_diff1": 0.55541,
                "nauc_recall_at_20_max": 0.539876,
                "nauc_recall_at_20_std": 0.077352,
                "nauc_recall_at_20_diff1": 0.506593,
                "nauc_recall_at_100_max": 0.492482,
                "nauc_recall_at_100_std": 0.100188,
                "nauc_recall_at_100_diff1": 0.465866,
                "nauc_recall_at_1000_max": NaN,
                "nauc_recall_at_1000_std": NaN,
                "nauc_recall_at_1000_diff1": NaN,
                "nauc_precision_at_1_max": 0.536972,
                "nauc_precision_at_1_std": 0.020363,
                "nauc_precision_at_1_diff1": 0.656342,
                "nauc_precision_at_3_max": 0.528593,
                "nauc_precision_at_3_std": 0.037015,
                "nauc_precision_at_3_diff1": 0.568422,
                "nauc_precision_at_5_max": 0.527509,
                "nauc_precision_at_5_std": 0.008924,
                "nauc_precision_at_5_diff1": 0.558105,
                "nauc_precision_at_10_max": 0.554046,
                "nauc_precision_at_10_std": 0.065361,
                "nauc_precision_at_10_diff1": 0.55541,
                "nauc_precision_at_20_max": 0.539876,
                "nauc_precision_at_20_std": 0.077352,
                "nauc_precision_at_20_diff1": 0.506593,
                "nauc_precision_at_100_max": 0.492482,
                "nauc_precision_at_100_std": 0.100188,
                "nauc_precision_at_100_diff1": 0.465866,
                "nauc_precision_at_1000_max": NaN,
                "nauc_precision_at_1000_std": NaN,
                "nauc_precision_at_1000_diff1": NaN,
                "nauc_mrr_at_1_max": 0.536972,
                "nauc_mrr_at_1_std": 0.020363,
                "nauc_mrr_at_1_diff1": 0.656342,
                "nauc_mrr_at_3_max": 0.532344,
                "nauc_mrr_at_3_std": 0.025791,
                "nauc_mrr_at_3_diff1": 0.618647,
                "nauc_mrr_at_5_max": 0.532084,
                "nauc_mrr_at_5_std": 0.020714,
                "nauc_mrr_at_5_diff1": 0.616964,
                "nauc_mrr_at_10_max": 0.536093,
                "nauc_mrr_at_10_std": 0.026747,
                "nauc_mrr_at_10_diff1": 0.618638,
                "nauc_mrr_at_20_max": 0.535546,
                "nauc_mrr_at_20_std": 0.027059,
                "nauc_mrr_at_20_diff1": 0.617044,
                "nauc_mrr_at_100_max": 0.535324,
                "nauc_mrr_at_100_std": 0.026918,
                "nauc_mrr_at_100_diff1": 0.617503,
                "nauc_mrr_at_1000_max": 0.535408,
                "nauc_mrr_at_1000_std": 0.0268,
                "nauc_mrr_at_1000_diff1": 0.617832,
                "main_score": 0.55192,
                "hf_subset": "eng_Latn-slk_Latn",
                "languages": [
                    "eng-Latn",
                    "slk-Latn"
                ]
            }
        ]
    },
    "evaluation_time": 2.1355416774749756,
    "kg_co2_emissions": null
}
