{
    "dataset_revision": "c5a6521a4ddce3450fb04ba218623681a9189c6d",
    "task_name": "SMESumRetrieval",
    "mteb_version": "1.39.7",
    "scores": {
        "test": [
            {
                "ndcg_at_1": 0.70667,
                "ndcg_at_3": 0.78367,
                "ndcg_at_5": 0.79808,
                "ndcg_at_10": 0.81532,
                "ndcg_at_20": 0.82553,
                "ndcg_at_100": 0.83128,
                "ndcg_at_1000": 0.83198,
                "map_at_1": 0.70667,
                "map_at_3": 0.76528,
                "map_at_5": 0.77328,
                "map_at_10": 0.78038,
                "map_at_20": 0.78324,
                "map_at_100": 0.78409,
                "map_at_1000": 0.78412,
                "recall_at_1": 0.70667,
                "recall_at_3": 0.83667,
                "recall_at_5": 0.87167,
                "recall_at_10": 0.925,
                "recall_at_20": 0.965,
                "recall_at_100": 0.995,
                "recall_at_1000": 1.0,
                "accuracy": 0.70667,
                "precision_at_1": 0.70667,
                "precision_at_3": 0.27889,
                "precision_at_5": 0.17433,
                "precision_at_10": 0.0925,
                "precision_at_20": 0.04825,
                "precision_at_100": 0.00995,
                "precision_at_1000": 0.001,
                "mrr_at_1": 0.706667,
                "mrr_at_3": 0.765278,
                "mrr_at_5": 0.773278,
                "mrr_at_10": 0.780385,
                "mrr_at_20": 0.783238,
                "mrr_at_100": 0.784087,
                "mrr_at_1000": 0.784125,
                "nauc_ndcg_at_1_max": 0.591813,
                "nauc_ndcg_at_1_std": -0.168653,
                "nauc_ndcg_at_1_diff1": 0.830554,
                "nauc_ndcg_at_3_max": 0.606022,
                "nauc_ndcg_at_3_std": -0.173484,
                "nauc_ndcg_at_3_diff1": 0.797422,
                "nauc_ndcg_at_5_max": 0.608143,
                "nauc_ndcg_at_5_std": -0.194718,
                "nauc_ndcg_at_5_diff1": 0.794191,
                "nauc_ndcg_at_10_max": 0.609443,
                "nauc_ndcg_at_10_std": -0.165704,
                "nauc_ndcg_at_10_diff1": 0.793406,
                "nauc_ndcg_at_20_max": 0.611793,
                "nauc_ndcg_at_20_std": -0.161434,
                "nauc_ndcg_at_20_diff1": 0.798432,
                "nauc_ndcg_at_100_max": 0.608514,
                "nauc_ndcg_at_100_std": -0.165653,
                "nauc_ndcg_at_100_diff1": 0.803222,
                "nauc_ndcg_at_1000_max": 0.607318,
                "nauc_ndcg_at_1000_std": -0.16928,
                "nauc_ndcg_at_1000_diff1": 0.802929,
                "nauc_map_at_1_max": 0.591813,
                "nauc_map_at_1_std": -0.168653,
                "nauc_map_at_1_diff1": 0.830554,
                "nauc_map_at_3_max": 0.602631,
                "nauc_map_at_3_std": -0.171103,
                "nauc_map_at_3_diff1": 0.806457,
                "nauc_map_at_5_max": 0.603643,
                "nauc_map_at_5_std": -0.182092,
                "nauc_map_at_5_diff1": 0.805196,
                "nauc_map_at_10_max": 0.604278,
                "nauc_map_at_10_std": -0.171272,
                "nauc_map_at_10_diff1": 0.805115,
                "nauc_map_at_20_max": 0.604833,
                "nauc_map_at_20_std": -0.169862,
                "nauc_map_at_20_diff1": 0.806323,
                "nauc_map_at_100_max": 0.604516,
                "nauc_map_at_100_std": -0.1707,
                "nauc_map_at_100_diff1": 0.80685,
                "nauc_map_at_1000_max": 0.604466,
                "nauc_map_at_1000_std": -0.170846,
                "nauc_map_at_1000_diff1": 0.806838,
                "nauc_recall_at_1_max": 0.591813,
                "nauc_recall_at_1_std": -0.168653,
                "nauc_recall_at_1_diff1": 0.830554,
                "nauc_recall_at_3_max": 0.618865,
                "nauc_recall_at_3_std": -0.183344,
                "nauc_recall_at_3_diff1": 0.762425,
                "nauc_recall_at_5_max": 0.629141,
                "nauc_recall_at_5_std": -0.258731,
                "nauc_recall_at_5_diff1": 0.742012,
                "nauc_recall_at_10_max": 0.647422,
                "nauc_recall_at_10_std": -0.103538,
                "nauc_recall_at_10_diff1": 0.704378,
                "nauc_recall_at_20_max": 0.727802,
                "nauc_recall_at_20_std": 0.020386,
                "nauc_recall_at_20_diff1": 0.695278,
                "nauc_recall_at_100_max": 0.863834,
                "nauc_recall_at_100_std": 0.615002,
                "nauc_recall_at_100_diff1": 0.863834,
                "nauc_recall_at_1000_max": NaN,
                "nauc_recall_at_1000_std": NaN,
                "nauc_recall_at_1000_diff1": NaN,
                "nauc_precision_at_1_max": 0.591813,
                "nauc_precision_at_1_std": -0.168653,
                "nauc_precision_at_1_diff1": 0.830554,
                "nauc_precision_at_3_max": 0.618865,
                "nauc_precision_at_3_std": -0.183344,
                "nauc_precision_at_3_diff1": 0.762425,
                "nauc_precision_at_5_max": 0.629141,
                "nauc_precision_at_5_std": -0.258731,
                "nauc_precision_at_5_diff1": 0.742012,
                "nauc_precision_at_10_max": 0.647422,
                "nauc_precision_at_10_std": -0.103538,
                "nauc_precision_at_10_diff1": 0.704378,
                "nauc_precision_at_20_max": 0.727802,
                "nauc_precision_at_20_std": 0.020386,
                "nauc_precision_at_20_diff1": 0.695278,
                "nauc_precision_at_100_max": 0.863834,
                "nauc_precision_at_100_std": 0.615002,
                "nauc_precision_at_100_diff1": 0.863834,
                "nauc_precision_at_1000_max": 1.0,
                "nauc_precision_at_1000_std": 1.0,
                "nauc_precision_at_1000_diff1": 1.0,
                "nauc_mrr_at_1_max": 0.591813,
                "nauc_mrr_at_1_std": -0.168653,
                "nauc_mrr_at_1_diff1": 0.830554,
                "nauc_mrr_at_3_max": 0.602631,
                "nauc_mrr_at_3_std": -0.171103,
                "nauc_mrr_at_3_diff1": 0.806457,
                "nauc_mrr_at_5_max": 0.603643,
                "nauc_mrr_at_5_std": -0.182092,
                "nauc_mrr_at_5_diff1": 0.805196,
                "nauc_mrr_at_10_max": 0.604278,
                "nauc_mrr_at_10_std": -0.171272,
                "nauc_mrr_at_10_diff1": 0.805115,
                "nauc_mrr_at_20_max": 0.604833,
                "nauc_mrr_at_20_std": -0.169862,
                "nauc_mrr_at_20_diff1": 0.806323,
                "nauc_mrr_at_100_max": 0.604516,
                "nauc_mrr_at_100_std": -0.1707,
                "nauc_mrr_at_100_diff1": 0.80685,
                "nauc_mrr_at_1000_max": 0.604466,
                "nauc_mrr_at_1000_std": -0.170846,
                "nauc_mrr_at_1000_diff1": 0.806838,
                "cv_recall_at_1": 0.70667,
                "cv_recall_at_3": 0.83667,
                "cv_recall_at_5": 0.87167,
                "cv_recall_at_10": 0.925,
                "cv_recall_at_20": 0.965,
                "cv_recall_at_100": 0.995,
                "cv_recall_at_1000": 1.0,
                "main_score": 0.81532,
                "hf_subset": "default",
                "languages": [
                    "slk-Latn"
                ]
            }
        ]
    },
    "evaluation_time": 2.3676400184631348,
    "kg_co2_emissions": null
}
