{
  "dataset_revision": "f64f483ad0f31d2e78209d524c14a4a867965959",
  "task_name": "WebFAQRetrieval",
  "mteb_version": "2.3.0",
  "scores": {
    "test": [
      {
        "ndcg_at_1": 0.77482,
        "ndcg_at_3": 0.84274,
        "ndcg_at_5": 0.85541,
        "ndcg_at_10": 0.86463,
        "ndcg_at_20": 0.86968,
        "ndcg_at_100": 0.87444,
        "ndcg_at_1000": 0.8754,
        "map_at_1": 0.77482,
        "map_at_3": 0.82667,
        "map_at_5": 0.8337,
        "map_at_10": 0.83749,
        "map_at_20": 0.83893,
        "map_at_100": 0.83965,
        "map_at_1000": 0.8397,
        "recall_at_1": 0.77482,
        "recall_at_3": 0.88899,
        "recall_at_5": 0.91976,
        "recall_at_10": 0.9483,
        "recall_at_20": 0.96797,
        "recall_at_100": 0.99271,
        "recall_at_1000": 0.99968,
        "accuracy": 0.77482,
        "precision_at_1": 0.77482,
        "precision_at_3": 0.29633,
        "precision_at_5": 0.18395,
        "precision_at_10": 0.09483,
        "precision_at_20": 0.0484,
        "precision_at_100": 0.00993,
        "precision_at_1000": 0.001,
        "mrr_at_1": 0.774818,
        "mrr_at_3": 0.826937,
        "mrr_at_5": 0.833883,
        "mrr_at_10": 0.837711,
        "mrr_at_20": 0.839051,
        "mrr_at_100": 0.839805,
        "mrr_at_1000": 0.839852,
        "nauc_ndcg_at_1_max": 0.562686,
        "nauc_ndcg_at_1_std": -0.179718,
        "nauc_ndcg_at_1_diff1": 0.850715,
        "nauc_ndcg_at_3_max": 0.579835,
        "nauc_ndcg_at_3_std": -0.256362,
        "nauc_ndcg_at_3_diff1": 0.828445,
        "nauc_ndcg_at_5_max": 0.578296,
        "nauc_ndcg_at_5_std": -0.263142,
        "nauc_ndcg_at_5_diff1": 0.82606,
        "nauc_ndcg_at_10_max": 0.57734,
        "nauc_ndcg_at_10_std": -0.259543,
        "nauc_ndcg_at_10_diff1": 0.82982,
        "nauc_ndcg_at_20_max": 0.575714,
        "nauc_ndcg_at_20_std": -0.252968,
        "nauc_ndcg_at_20_diff1": 0.832696,
        "nauc_ndcg_at_100_max": 0.575054,
        "nauc_ndcg_at_100_std": -0.240601,
        "nauc_ndcg_at_100_diff1": 0.834306,
        "nauc_ndcg_at_1000_max": 0.574292,
        "nauc_ndcg_at_1000_std": -0.241316,
        "nauc_ndcg_at_1000_diff1": 0.834103,
        "nauc_map_at_1_max": 0.562686,
        "nauc_map_at_1_std": -0.179718,
        "nauc_map_at_1_diff1": 0.850715,
        "nauc_map_at_3_max": 0.574675,
        "nauc_map_at_3_std": -0.23548,
        "nauc_map_at_3_diff1": 0.834814,
        "nauc_map_at_5_max": 0.573709,
        "nauc_map_at_5_std": -0.238131,
        "nauc_map_at_5_diff1": 0.833908,
        "nauc_map_at_10_max": 0.573254,
        "nauc_map_at_10_std": -0.236916,
        "nauc_map_at_10_diff1": 0.835325,
        "nauc_map_at_20_max": 0.572709,
        "nauc_map_at_20_std": -0.235328,
        "nauc_map_at_20_diff1": 0.835981,
        "nauc_map_at_100_max": 0.572544,
        "nauc_map_at_100_std": -0.233842,
        "nauc_map_at_100_diff1": 0.836177,
        "nauc_map_at_1000_max": 0.572527,
        "nauc_map_at_1000_std": -0.23382,
        "nauc_map_at_1000_diff1": 0.836167,
        "nauc_recall_at_1_max": 0.562686,
        "nauc_recall_at_1_std": -0.179718,
        "nauc_recall_at_1_diff1": 0.850715,
        "nauc_recall_at_3_max": 0.601786,
        "nauc_recall_at_3_std": -0.343865,
        "nauc_recall_at_3_diff1": 0.80155,
        "nauc_recall_at_5_max": 0.60342,
        "nauc_recall_at_5_std": -0.401857,
        "nauc_recall_at_5_diff1": 0.782026,
        "nauc_recall_at_10_max": 0.610157,
        "nauc_recall_at_10_std": -0.440914,
        "nauc_recall_at_10_diff1": 0.787581,
        "nauc_recall_at_20_max": 0.610767,
        "nauc_recall_at_20_std": -0.449615,
        "nauc_recall_at_20_diff1": 0.806495,
        "nauc_recall_at_100_max": 0.694885,
        "nauc_recall_at_100_std": -0.063381,
        "nauc_recall_at_100_diff1": 0.857003,
        "nauc_recall_at_1000_max": 1.0,
        "nauc_recall_at_1000_std": 0.869295,
        "nauc_recall_at_1000_diff1": 0.869295,
        "nauc_precision_at_1_max": 0.562686,
        "nauc_precision_at_1_std": -0.179718,
        "nauc_precision_at_1_diff1": 0.850715,
        "nauc_precision_at_3_max": 0.601786,
        "nauc_precision_at_3_std": -0.343865,
        "nauc_precision_at_3_diff1": 0.80155,
        "nauc_precision_at_5_max": 0.60342,
        "nauc_precision_at_5_std": -0.401857,
        "nauc_precision_at_5_diff1": 0.782026,
        "nauc_precision_at_10_max": 0.610157,
        "nauc_precision_at_10_std": -0.440914,
        "nauc_precision_at_10_diff1": 0.787581,
        "nauc_precision_at_20_max": 0.610767,
        "nauc_precision_at_20_std": -0.449615,
        "nauc_precision_at_20_diff1": 0.806495,
        "nauc_precision_at_100_max": 0.694885,
        "nauc_precision_at_100_std": -0.063381,
        "nauc_precision_at_100_diff1": 0.857003,
        "nauc_precision_at_1000_max": 1.0,
        "nauc_precision_at_1000_std": 0.869295,
        "nauc_precision_at_1000_diff1": 0.869295,
        "nauc_mrr_at_1_max": 0.562686,
        "nauc_mrr_at_1_std": -0.179718,
        "nauc_mrr_at_1_diff1": 0.850715,
        "nauc_mrr_at_3_max": 0.57473,
        "nauc_mrr_at_3_std": -0.233675,
        "nauc_mrr_at_3_diff1": 0.834408,
        "nauc_mrr_at_5_max": 0.572807,
        "nauc_mrr_at_5_std": -0.237355,
        "nauc_mrr_at_5_diff1": 0.83368,
        "nauc_mrr_at_10_max": 0.572534,
        "nauc_mrr_at_10_std": -0.236284,
        "nauc_mrr_at_10_diff1": 0.835093,
        "nauc_mrr_at_20_max": 0.572204,
        "nauc_mrr_at_20_std": -0.23497,
        "nauc_mrr_at_20_diff1": 0.835759,
        "nauc_mrr_at_100_max": 0.571969,
        "nauc_mrr_at_100_std": -0.23327,
        "nauc_mrr_at_100_diff1": 0.835955,
        "nauc_mrr_at_1000_max": 0.571952,
        "nauc_mrr_at_1000_std": -0.233248,
        "nauc_mrr_at_1000_diff1": 0.835945,
        "cv_recall_at_1": 0.77482,
        "cv_recall_at_3": 0.88963,
        "cv_recall_at_5": 0.92008,
        "cv_recall_at_10": 0.94894,
        "cv_recall_at_20": 0.96733,
        "cv_recall_at_100": 0.99271,
        "cv_recall_at_1000": 0.99968,
        "main_score": 0.86463,
        "hf_subset": "slk",
        "languages": [
          "slk-Latn"
        ]
      }
    ]
  },
  "evaluation_time": 194.29239797592163,
  "kg_co2_emissions": null
}