{
    "dataset_revision": "c5a6521a4ddce3450fb04ba218623681a9189c6d",
    "task_name": "SMESumCategoryClustering",
    "mteb_version": "1.39.7",
    "scores": {
        "test": [
            {
                "v_measures": {
                    "Level 0": [
                        0.220612,
                        0.244243,
                        0.286304,
                        0.272386,
                        0.236067,
                        0.27325,
                        0.307283,
                        0.250129,
                        0.337525,
                        0.334132
                    ]
                },
                "v_measure": 0.276193,
                "v_measure_std": 0.038223,
                "main_score": 0.276193,
                "hf_subset": "default",
                "languages": [
                    "slk-Latn"
                ]
            }
        ]
    },
    "evaluation_time": 6.167671203613281,
    "kg_co2_emissions": null
}
