{
  "dataset_revision": "c5a6521a4ddce3450fb04ba218623681a9189c6d",
  "task_name": "SMESumRetrieval",
  "mteb_version": "2.3.0",
  "scores": {
    "test": [
      {
        "ndcg_at_1": 0.78833,
        "ndcg_at_3": 0.85758,
        "ndcg_at_5": 0.86862,
        "ndcg_at_10": 0.8775,
        "ndcg_at_20": 0.87954,
        "ndcg_at_100": 0.88501,
        "ndcg_at_1000": 0.88571,
        "map_at_1": 0.78833,
        "map_at_3": 0.84111,
        "map_at_5": 0.84728,
        "map_at_10": 0.85109,
        "map_at_20": 0.85162,
        "map_at_100": 0.85245,
        "map_at_1000": 0.85249,
        "recall_at_1": 0.78833,
        "recall_at_3": 0.905,
        "recall_at_5": 0.93167,
        "recall_at_10": 0.95833,
        "recall_at_20": 0.96667,
        "recall_at_100": 0.995,
        "recall_at_1000": 1.0,
        "accuracy": 0.78833,
        "precision_at_1": 0.78833,
        "precision_at_3": 0.30167,
        "precision_at_5": 0.18633,
        "precision_at_10": 0.09583,
        "precision_at_20": 0.04833,
        "precision_at_100": 0.00995,
        "precision_at_1000": 0.001,
        "mrr_at_1": 0.788333,
        "mrr_at_3": 0.841111,
        "mrr_at_5": 0.847278,
        "mrr_at_10": 0.851089,
        "mrr_at_20": 0.851616,
        "mrr_at_100": 0.852449,
        "mrr_at_1000": 0.852485,
        "nauc_ndcg_at_1_max": 0.694012,
        "nauc_ndcg_at_1_std": 0.046891,
        "nauc_ndcg_at_1_diff1": 0.874887,
        "nauc_ndcg_at_3_max": 0.752387,
        "nauc_ndcg_at_3_std": 0.077375,
        "nauc_ndcg_at_3_diff1": 0.86565,
        "nauc_ndcg_at_5_max": 0.752525,
        "nauc_ndcg_at_5_std": 0.080801,
        "nauc_ndcg_at_5_diff1": 0.867997,
        "nauc_ndcg_at_10_max": 0.753151,
        "nauc_ndcg_at_10_std": 0.106289,
        "nauc_ndcg_at_10_diff1": 0.872383,
        "nauc_ndcg_at_20_max": 0.749218,
        "nauc_ndcg_at_20_std": 0.10558,
        "nauc_ndcg_at_20_diff1": 0.870532,
        "nauc_ndcg_at_100_max": 0.743193,
        "nauc_ndcg_at_100_std": 0.095018,
        "nauc_ndcg_at_100_diff1": 0.87186,
        "nauc_ndcg_at_1000_max": 0.74181,
        "nauc_ndcg_at_1000_std": 0.089735,
        "nauc_ndcg_at_1000_diff1": 0.871631,
        "nauc_map_at_1_max": 0.694012,
        "nauc_map_at_1_std": 0.046891,
        "nauc_map_at_1_diff1": 0.874887,
        "nauc_map_at_3_max": 0.737414,
        "nauc_map_at_3_std": 0.070477,
        "nauc_map_at_3_diff1": 0.86875,
        "nauc_map_at_5_max": 0.73699,
        "nauc_map_at_5_std": 0.071983,
        "nauc_map_at_5_diff1": 0.869939,
        "nauc_map_at_10_max": 0.736839,
        "nauc_map_at_10_std": 0.081245,
        "nauc_map_at_10_diff1": 0.871694,
        "nauc_map_at_20_max": 0.735957,
        "nauc_map_at_20_std": 0.080962,
        "nauc_map_at_20_diff1": 0.871288,
        "nauc_map_at_100_max": 0.735281,
        "nauc_map_at_100_std": 0.079945,
        "nauc_map_at_100_diff1": 0.87159,
        "nauc_map_at_1000_max": 0.735224,
        "nauc_map_at_1000_std": 0.07973,
        "nauc_map_at_1000_diff1": 0.871581,
        "nauc_recall_at_1_max": 0.694012,
        "nauc_recall_at_1_std": 0.046891,
        "nauc_recall_at_1_diff1": 0.874887,
        "nauc_recall_at_3_max": 0.818476,
        "nauc_recall_at_3_std": 0.10709,
        "nauc_recall_at_3_diff1": 0.851385,
        "nauc_recall_at_5_max": 0.84357,
        "nauc_recall_at_5_std": 0.132552,
        "nauc_recall_at_5_diff1": 0.85687,
        "nauc_recall_at_10_max": 0.906088,
        "nauc_recall_at_10_std": 0.370663,
        "nauc_recall_at_10_diff1": 0.88394,
        "nauc_recall_at_20_max": 0.889146,
        "nauc_recall_at_20_std": 0.428151,
        "nauc_recall_at_20_diff1": 0.861461,
        "nauc_recall_at_100_max": 0.956427,
        "nauc_recall_at_100_std": 0.907407,
        "nauc_recall_at_100_diff1": 0.907407,
        "nauc_recall_at_1000_max": NaN,
        "nauc_recall_at_1000_std": NaN,
        "nauc_recall_at_1000_diff1": NaN,
        "nauc_precision_at_1_max": 0.694012,
        "nauc_precision_at_1_std": 0.046891,
        "nauc_precision_at_1_diff1": 0.874887,
        "nauc_precision_at_3_max": 0.818476,
        "nauc_precision_at_3_std": 0.10709,
        "nauc_precision_at_3_diff1": 0.851385,
        "nauc_precision_at_5_max": 0.84357,
        "nauc_precision_at_5_std": 0.132552,
        "nauc_precision_at_5_diff1": 0.85687,
        "nauc_precision_at_10_max": 0.906088,
        "nauc_precision_at_10_std": 0.370663,
        "nauc_precision_at_10_diff1": 0.88394,
        "nauc_precision_at_20_max": 0.889146,
        "nauc_precision_at_20_std": 0.428151,
        "nauc_precision_at_20_diff1": 0.861461,
        "nauc_precision_at_100_max": 0.956427,
        "nauc_precision_at_100_std": 0.907407,
        "nauc_precision_at_100_diff1": 0.907407,
        "nauc_precision_at_1000_max": 1.0,
        "nauc_precision_at_1000_std": 1.0,
        "nauc_precision_at_1000_diff1": 1.0,
        "nauc_mrr_at_1_max": 0.694012,
        "nauc_mrr_at_1_std": 0.046891,
        "nauc_mrr_at_1_diff1": 0.874887,
        "nauc_mrr_at_3_max": 0.737414,
        "nauc_mrr_at_3_std": 0.070477,
        "nauc_mrr_at_3_diff1": 0.86875,
        "nauc_mrr_at_5_max": 0.73699,
        "nauc_mrr_at_5_std": 0.071983,
        "nauc_mrr_at_5_diff1": 0.869939,
        "nauc_mrr_at_10_max": 0.736839,
        "nauc_mrr_at_10_std": 0.081245,
        "nauc_mrr_at_10_diff1": 0.871694,
        "nauc_mrr_at_20_max": 0.735957,
        "nauc_mrr_at_20_std": 0.080962,
        "nauc_mrr_at_20_diff1": 0.871288,
        "nauc_mrr_at_100_max": 0.735281,
        "nauc_mrr_at_100_std": 0.079945,
        "nauc_mrr_at_100_diff1": 0.87159,
        "nauc_mrr_at_1000_max": 0.735224,
        "nauc_mrr_at_1000_std": 0.07973,
        "nauc_mrr_at_1000_diff1": 0.871581,
        "cv_recall_at_1": 0.78833,
        "cv_recall_at_3": 0.905,
        "cv_recall_at_5": 0.93167,
        "cv_recall_at_10": 0.95833,
        "cv_recall_at_20": 0.96667,
        "cv_recall_at_100": 0.995,
        "cv_recall_at_1000": 1.0,
        "main_score": 0.8775,
        "hf_subset": "default",
        "languages": [
          "slk-Latn"
        ]
      }
    ]
  },
  "evaluation_time": 296.2014901638031,
  "kg_co2_emissions": null
}