{
    "dataset_revision": "a74d7350ea12af010cfb1c21e34f1f81fd2e615b",
    "task_name": "SIB200ClusteringS2S",
    "mteb_version": "1.39.7",
    "scores": {
        "test": [
            {
                "v_measures": {
                    "Level 0": [
                        0.385443,
                        0.433287,
                        0.452177,
                        0.413103,
                        0.494159,
                        0.429912,
                        0.378636,
                        0.454427,
                        0.385189,
                        0.495367
                    ]
                },
                "v_measure": 0.43217,
                "v_measure_std": 0.040446,
                "main_score": 0.43217,
                "hf_subset": "slk_Latn",
                "languages": [
                    "slk-Latn"
                ]
            }
        ]
    },
    "evaluation_time": 6.932124614715576,
    "kg_co2_emissions": null
}
