{
    "dataset_revision": "a74d7350ea12af010cfb1c21e34f1f81fd2e615b",
    "task_name": "SIB200ClusteringS2S",
    "mteb_version": "1.39.7",
    "scores": {
        "test": [
            {
                "v_measures": {
                    "Level 0": [
                        0.242402,
                        0.312902,
                        0.314988,
                        0.26753,
                        0.315266,
                        0.290174,
                        0.321934,
                        0.26749,
                        0.296401,
                        0.331583
                    ]
                },
                "v_measure": 0.296067,
                "v_measure_std": 0.027361,
                "main_score": 0.296067,
                "hf_subset": "slk_Latn",
                "languages": [
                    "slk-Latn"
                ]
            }
        ]
    },
    "evaluation_time": 7.891148805618286,
    "kg_co2_emissions": null
}
