{
  "dataset_revision": "dd0a6c077151b8c8bc2fd6abcd746b34fde80bf8",
  "task_name": "PravdaSKTagClustering",
  "mteb_version": "2.3.0",
  "scores": {
    "test": [
      {
        "v_measures": {
          "Level 0": [
            0.583203,
            0.626605,
            0.607699,
            0.609491,
            0.582164,
            0.583565,
            0.526953,
            0.579681,
            0.594897,
            0.586478
          ]
        },
        "v_measure": 0.588074,
        "v_measure_std": 0.025026,
        "main_score": 0.588074,
        "hf_subset": "default",
        "languages": [
          "slk-Latn"
        ]
      }
    ]
  },
  "evaluation_time": 20.19832181930542,
  "kg_co2_emissions": null
}